hpverif/Calibraton.py
hpverif/Driver.py
hpverif/FrameCapture.py
hpverif/FrameCapturePLY.py
hpverif/PointCloud.py
hpverif/Segmentation.py
hpverif/ShowFiles.py
hpverif/Theoretical_distance.py
hpverif/Verification.py
hpverif/__init__.py
hpverif/driver.py
hpverif-2.6.4.dist-info/METADATA
hpverif-2.6.4.dist-info/WHEEL
hpverif-2.6.4.dist-info/top_level.txt
hpverif-2.6.4.dist-info/RECORD
