Metadata-Version: 2.1
Name: hpverif
Version: 2.6.4
Summary: Construction verification library PAE 2023
Author: Telecos PAE 2023 Students
License: MIT
Requires-Dist: pyrealsense2
Requires-Dist: numpy
Requires-Dist: opencv-python
Requires-Dist: matplotlib
Requires-Dist: scipy
Requires-Dist: open3d
Requires-Dist: imageio
